odoo10_addon_l10n_it_website_sale_fiscalcode-10.0.1.0.2-nspkg.pth
odoo/addons/l10n_it_website_sale_fiscalcode/README.rst
odoo/addons/l10n_it_website_sale_fiscalcode/__init__.py
odoo/addons/l10n_it_website_sale_fiscalcode/__manifest__.py
odoo/addons/l10n_it_website_sale_fiscalcode/controllers/__init__.py
odoo/addons/l10n_it_website_sale_fiscalcode/controllers/main.py
odoo/addons/l10n_it_website_sale_fiscalcode/i18n/de.po
odoo/addons/l10n_it_website_sale_fiscalcode/i18n/es.po
odoo/addons/l10n_it_website_sale_fiscalcode/i18n/it.po
odoo/addons/l10n_it_website_sale_fiscalcode/i18n/l10n_it_website_sale_fiscalcode.pot
odoo/addons/l10n_it_website_sale_fiscalcode/i18n/sl.po
odoo/addons/l10n_it_website_sale_fiscalcode/static/description/icon.png
odoo/addons/l10n_it_website_sale_fiscalcode/views/templates.xml
odoo10_addon_l10n_it_website_sale_fiscalcode-10.0.1.0.2.dist-info/METADATA
odoo10_addon_l10n_it_website_sale_fiscalcode-10.0.1.0.2.dist-info/WHEEL
odoo10_addon_l10n_it_website_sale_fiscalcode-10.0.1.0.2.dist-info/namespace_packages.txt
odoo10_addon_l10n_it_website_sale_fiscalcode-10.0.1.0.2.dist-info/top_level.txt
odoo10_addon_l10n_it_website_sale_fiscalcode-10.0.1.0.2.dist-info/RECORD
