Metadata-Version: 2.1
Name: odoo10-addon-l10n-it-website-sale-fiscalcode
Version: 10.0.1.0.2
Summary: Website Sale FiscalCode
Home-page: http://www.agilebg.com
Author: Agile Business Group,Odoo Community Association (OCA)
Author-email: support@odoo-community.org
License: LGPL-3
Platform: UNKNOWN
Classifier: Programming Language :: Python
Classifier: Framework :: Odoo
Classifier: License :: OSI Approved :: GNU Lesser General Public License v3 (LGPLv3)
Requires-Python: ~=2.7
Requires-Dist: odoo10-addon-l10n-it-fiscalcode
Requires-Dist: odoo (<10.1dev,>=10.0)
